aquacheck/__init__.py
aquacheck/main.py
EnviroChlor_Water_Disinfection_with_Chlorine_based_on_DO_Temperature_and_NTU-0.0.0.dist-info/LICENSE
EnviroChlor_Water_Disinfection_with_Chlorine_based_on_DO_Temperature_and_NTU-0.0.0.dist-info/METADATA
EnviroChlor_Water_Disinfection_with_Chlorine_based_on_DO_Temperature_and_NTU-0.0.0.dist-info/WHEEL
EnviroChlor_Water_Disinfection_with_Chlorine_based_on_DO_Temperature_and_NTU-0.0.0.dist-info/top_level.txt
EnviroChlor_Water_Disinfection_with_Chlorine_based_on_DO_Temperature_and_NTU-0.0.0.dist-info/RECORD
